SungrowModbusTcpClient/SungrowModbusTcpClient.py
SungrowModbusTcpClient/__init__.py
SungrowModbusTcpClient_jesseklm-0.1.9.dist-info/LICENSE
SungrowModbusTcpClient_jesseklm-0.1.9.dist-info/METADATA
SungrowModbusTcpClient_jesseklm-0.1.9.dist-info/WHEEL
SungrowModbusTcpClient_jesseklm-0.1.9.dist-info/top_level.txt
SungrowModbusTcpClient_jesseklm-0.1.9.dist-info/RECORD
